input_helper/__init__.py
input_helper/matcher.py
tests/__init__.py
tests/test_init.py
tests/test_matcher.py
input_helper-0.1.54.dist-info/LICENSE.txt
input_helper-0.1.54.dist-info/METADATA
input_helper-0.1.54.dist-info/WHEEL
input_helper-0.1.54.dist-info/top_level.txt
input_helper-0.1.54.dist-info/RECORD
