Metadata-Version: 2.1
Name: input-helper
Version: 0.1.54
Summary: Helpers for parsing user input, generating menus, transforming data, making comparisons, flexible argument acceptance (string to list/set), regex matching, and more
Home-page: https://github.com/kenjyco/input-helper
Author: Ken
Author-email: kenjyco@gmail.com
License: MIT
Download-URL: https://github.com/kenjyco/input-helper/tarball/v0.1.54
Keywords: input,user input,regex,matching,json,selection,menus,filtering,conversions,transformations,comparisons,cli,command-line,helper,kenjyco
Platform: UNKNOWN
Classifier: Development Status :: 4 - Beta
Classifier: Environment :: Console
Classifier: Framework :: IPython
Classifier: Intended Audience :: Developers
Classifier: License :: OSI Approved :: MIT License
Classifier: Operating System :: MacOS :: MacOS X
Classifier: Operating System :: POSIX :: Linux
Classifier: Programming Language :: Python :: 3.5
Classifier: Programming Language :: Python :: 3.6
Classifier: Programming Language :: Python :: 3.7
Classifier: Programming Language :: Python :: 3.8
Classifier: Programming Language :: Python :: 3.9
Classifier: Programming Language :: Python :: 3.10
Classifier: Programming Language :: Python :: 3.11
Classifier: Programming Language :: Python :: 3.12
Classifier: Programming Language :: Python :: 3.13
Classifier: Programming Language :: Python
Classifier: Topic :: Software Development :: Libraries
Classifier: Topic :: System :: Shells
Classifier: Topic :: Text Processing :: Filters
Classifier: Topic :: Text Processing :: General
Classifier: Topic :: Text Processing :: Markup :: XML
Classifier: Topic :: Utilities
Provides-Extra: full
Requires-Dist: ipython; extra == "full"
Requires-Dist: xmljson; extra == "full"
Provides-Extra: ipython
Requires-Dist: ipython; extra == "ipython"
Provides-Extra: xmljson
Requires-Dist: xmljson; extra == "xmljson"
